innerscope/__init__.py
innerscope/cfg.py
innerscope/core.py
innerscope/tests/__init__.py
innerscope/tests/conftest.py
innerscope/tests/test_core.py
innerscope/tests/test_repr.py
innerscope-0.7.0.dist-info/LICENSE
innerscope-0.7.0.dist-info/METADATA
innerscope-0.7.0.dist-info/WHEEL
innerscope-0.7.0.dist-info/top_level.txt
innerscope-0.7.0.dist-info/RECORD
