Metadata-Version: 2.1
Name: innerscope
Version: 0.7.0
Summary: Expose the inner scope of functions
Author: Innerscope contributors
Author-email: Erik Welch <erik.n.welch@gmail.com>
Maintainer-email: Erik Welch <erik.n.welch@gmail.com>
License: Copyright (c) 2020 Erik Welch
Project-URL: homepage, https://github.com/eriknw/innerscope
Project-URL: repository, https://github.com/eriknw/innerscope
Project-URL: changelog, https://github.com/eriknw/innerscope/releases
Keywords: introspection,dict,utility,bytecode
Classifier: Development Status :: 4 - Beta
Classifier: License :: OSI Approved :: BSD License
Classifier: Operating System :: OS Independent
Classifier: Programming Language :: Python
Classifier: Programming Language :: Python :: 3
Classifier: Programming Language :: Python :: 3.8
Classifier: Programming Language :: Python :: 3.9
Classifier: Programming Language :: Python :: 3.10
Classifier: Programming Language :: Python :: 3.11
Classifier: Programming Language :: Python :: 3.12
Classifier: Programming Language :: Python :: 3 :: Only
Classifier: Programming Language :: Python :: Implementation :: CPython
Classifier: Programming Language :: Python :: Implementation :: PyPy
Classifier: Intended Audience :: Developers
Classifier: Intended Audience :: Other Audience
Classifier: Topic :: Software Development :: Libraries :: Python Modules
Requires-Python: >=3.8
License-File: LICENSE
Requires-Dist: toolz
Provides-Extra: test
Requires-Dist: pytest>=6; extra == "test"
